netzip/__init__.py
netzip-0.3.1.dist-info/LICENSE.txt
netzip-0.3.1.dist-info/METADATA
netzip-0.3.1.dist-info/WHEEL
netzip-0.3.1.dist-info/top_level.txt
netzip-0.3.1.dist-info/RECORD
