Metadata-Version: 2.1
Name: netzip
Version: 0.3.1
Summary: ZIP file reader optimized for network access
Author-email: Emil Melnikov <emilmelnikov@gmail.com>
License: MIT
Project-URL: Homepage, https://github.com/ilastik/netzip
Project-URL: Bug Tracker, https://github.com/ilastik/netzip/issues
Project-URL: Source, https://github.com/ilastik/netzip
Requires-Python: >=3.8
License-File: LICENSE.txt
